welcome_wizard/__init__.py
welcome_wizard/admin.py
welcome_wizard/api/__init__.py
welcome_wizard/api/serializers.py
welcome_wizard/api/urls.py
welcome_wizard/api/views.py
welcome_wizard/app-config-schema.json
welcome_wizard/banner.py
welcome_wizard/datasources.py
welcome_wizard/filters.py
welcome_wizard/forms.py
welcome_wizard/jobs.py
welcome_wizard/middleware.py
welcome_wizard/migrations/0001_initial.py
welcome_wizard/migrations/0002_merlin_nautobot_list_link.py
welcome_wizard/migrations/0003_auto_20210705_1912.py
welcome_wizard/migrations/0004_remove_manufacturerimport_slug.py
welcome_wizard/migrations/0005_fix_sites_and_roles_in_merlin.py
welcome_wizard/migrations/0006_alter_merlin_options.py
welcome_wizard/migrations/__init__.py
welcome_wizard/models/__init__.py
welcome_wizard/models/importer.py
welcome_wizard/models/merlin.py
welcome_wizard/navigation.py
welcome_wizard/signals.py
welcome_wizard/tables.py
welcome_wizard/templates/welcome_wizard/devicetypeimport_list.html
welcome_wizard/templates/welcome_wizard/import.html
welcome_wizard/templates/welcome_wizard/manufacturerimport_list.html
welcome_wizard/tests/__init__.py
welcome_wizard/tests/fixtures/device-types/device_type_fixture1.yaml
welcome_wizard/tests/fixtures/device-types/device_type_fixture2.yaml
welcome_wizard/tests/fixtures/device-types/device_type_fixture3.yaml
welcome_wizard/tests/test_api.py
welcome_wizard/tests/test_datasources.py
welcome_wizard/tests/test_filters.py
welcome_wizard/tests/test_forms.py
welcome_wizard/tests/test_jobs.py
welcome_wizard/tests/test_models.py
welcome_wizard/tests/test_views.py
welcome_wizard/urls.py
welcome_wizard/views.py
nautobot_welcome_wizard-3.0.0.dist-info/LICENSE
nautobot_welcome_wizard-3.0.0.dist-info/METADATA
nautobot_welcome_wizard-3.0.0.dist-info/WHEEL
nautobot_welcome_wizard-3.0.0.dist-info/RECORD
