Metadata-Version: 2.3
Name: nautobot-welcome-wizard
Version: 3.0.0
Summary: Nautobot's Getting Started Wizard
License: Apache-2.0
Keywords: nautobot,nautobot-app,nautobot-plugin
Author: Network to Code, LLC
Author-email: info@networktocode.com
Requires-Python: >=3.10,<3.14
Classifier: Development Status :: 5 - Production/Stable
Classifier: Intended Audience :: Developers
Classifier: License :: OSI Approved :: Apache Software License
Classifier: Programming Language :: Python :: 3
Classifier: Programming Language :: Python :: 3.10
Classifier: Programming Language :: Python :: 3.11
Classifier: Programming Language :: Python :: 3.12
Classifier: Programming Language :: Python :: 3.13
Provides-Extra: all
Requires-Dist: nautobot (>=3.0.0,<4.0.0)
Project-URL: Documentation, https://docs.nautobot.com/projects/welcome-wizard/en/latest/
Project-URL: Homepage, https://github.com/nautobot/nautobot-app-welcome-wizard
Project-URL: Repository, https://github.com/nautobot/nautobot-app-welcome-wizard
